grainlearning/__init__.py
grainlearning/bayesian_calibration.py
grainlearning/dynamic_systems.py
grainlearning/inference.py
grainlearning/iterative_bayesian_filter.py
grainlearning/rnn/README.md
grainlearning/rnn/__init__.py
grainlearning/rnn/evaluate_model.py
grainlearning/rnn/models.py
grainlearning/rnn/predict.py
grainlearning/rnn/preprocessor.py
grainlearning/rnn/sweep/example_sweep.yaml
grainlearning/rnn/sweep/run_sweep.sh
grainlearning/rnn/train.py
grainlearning/rnn/trained_models/rnn_triaxial_drained/config.yml
grainlearning/rnn/trained_models/rnn_triaxial_drained/model-best.h5
grainlearning/rnn/trained_models/rnn_triaxial_drained/requirements.txt
grainlearning/rnn/trained_models/rnn_triaxial_drained/train_stats.npy
grainlearning/rnn/trained_models/rnn_triaxial_drained+e0/config.yml
grainlearning/rnn/trained_models/rnn_triaxial_drained+e0/model-best.h5
grainlearning/rnn/trained_models/rnn_triaxial_drained+e0/requirements.txt
grainlearning/rnn/trained_models/rnn_triaxial_drained+e0/train_stats.npy
grainlearning/rnn/trained_models/rnn_triaxial_undrained/config.yml
grainlearning/rnn/trained_models/rnn_triaxial_undrained/model-best.h5
grainlearning/rnn/trained_models/rnn_triaxial_undrained/requirements.txt
grainlearning/rnn/trained_models/rnn_triaxial_undrained/train_stats.npy
grainlearning/rnn/trained_models/rnn_triaxial_undrained+e0/config.yml
grainlearning/rnn/trained_models/rnn_triaxial_undrained+e0/model-best.h5
grainlearning/rnn/trained_models/rnn_triaxial_undrained+e0/requirements.txt
grainlearning/rnn/trained_models/rnn_triaxial_undrained+e0/train_stats.npy
grainlearning/rnn/windows.py
grainlearning/sampling.py
grainlearning/tools.py
grainlearning-2.0.5.dist-info/LICENSE
grainlearning-2.0.5.dist-info/METADATA
grainlearning-2.0.5.dist-info/NOTICE
grainlearning-2.0.5.dist-info/WHEEL
grainlearning-2.0.5.dist-info/RECORD
