Metadata-Version: 2.1
Name: GrainLearning
Version: 2.0.5
Summary: A Bayesian uncertainty quantification toolbox for discrete and continuum numerical models of granular materials
Home-page: https://grainlearning.readthedocs.io/
License: GPLv2
Keywords: Bayesian inference,Uncertainty quantification,Non-parametric Gaussian mixture,DEM,Constitutive modeling,Granular materials
Author: Hongyang Cheng
Author-email: h.cheng@utwente.nl
Requires-Python: >=3.9,<3.14
Classifier: License :: Other/Proprietary License
Classifier: Programming Language :: Python :: 3
Classifier: Programming Language :: Python :: 3.9
Classifier: Programming Language :: Python :: 3.10
Classifier: Programming Language :: Python :: 3.11
Classifier: Programming Language :: Python :: 3.12
Classifier: Programming Language :: Python :: 3.13
Provides-Extra: dev
Provides-Extra: docs
Provides-Extra: rnn
Provides-Extra: tutorials
Provides-Extra: visuals
Requires-Dist: Sphinx (>=5.1.1,<6.0.0) ; extra == "docs"
Requires-Dist: h5py (>=3.12.1,<4.0.0) ; extra == "dev"
Requires-Dist: ipykernel ; extra == "dev" or extra == "tutorials"
Requires-Dist: matplotlib (>=3.6.0,<4.0.0)
Requires-Dist: numpy (>=1.23.2,<2.0.0)
Requires-Dist: prospector[with-pyroma] (>=1.7.6,<2.0.0) ; extra == "dev"
Requires-Dist: pyroma (>=4.0,<5.0) ; extra == "dev"
Requires-Dist: pytest (>=6.2.4,<7.0.0) ; extra == "dev"
Requires-Dist: pytest-cov (>=2.12.1,<3.0.0) ; extra == "dev"
Requires-Dist: scikit-learn (>=1.6.0,<2.0.0)
Requires-Dist: scipy (>=1.9.1,<2.0.0)
Requires-Dist: seaborn (>=0.13.2,<0.14.0) ; extra == "visuals"
Requires-Dist: sphinx-autodoc-typehints (>=1.19.2,<2.0.0) ; extra == "docs"
Requires-Dist: sphinx-mdinclude ; extra == "docs"
Requires-Dist: sphinx-rtd-theme (>=1.1.1) ; extra == "docs"
Requires-Dist: tensorflow (>=2.10.0,<3.0.0) ; extra == "dev" or extra == "rnn"
Requires-Dist: wandb (>=0.13.4,<0.14.0) ; extra == "dev" or extra == "rnn"
Project-URL: Repository, https://github.com/GrainLearning/grainLearning
